avenyn_lunch/AvenySession.py
avenyn_lunch/Restaurant.py
avenyn_lunch/__init__.py
avenyn_lunch/bin.py
avenyn_lunch/constants.py
avenyn_lunch-1.5.dist-info/DESCRIPTION.rst
avenyn_lunch-1.5.dist-info/METADATA
avenyn_lunch-1.5.dist-info/RECORD
avenyn_lunch-1.5.dist-info/WHEEL
avenyn_lunch-1.5.dist-info/entry_points.txt
avenyn_lunch-1.5.dist-info/metadata.json
avenyn_lunch-1.5.dist-info/top_level.txt
