Metadata-Version: 2.0
Name: avenyn-lunch
Version: 1.5
Summary: UNKNOWN
Home-page: UNKNOWN
Author: ianertson
Author-email: ianertson@gmail.com
License: UNKNOWN
Platform: UNKNOWN
Requires-Dist: bs4
Requires-Dist: requests
